fpq/__init__.py
fpq/fp.py
fpq/numba_wrapper.py
fpq/quaternion.py
fpq/utils.py
fpq/vector.py
fpq/version.py
fpq-0.11.0.dist-info/METADATA
fpq-0.11.0.dist-info/RECORD
fpq-0.11.0.dist-info/WHEEL
fpq-0.11.0.dist-info/top_level.txt
