Metadata-Version: 2.1
Name: fpq
Version: 0.11.0
Summary: This package provides modules for manipulating floating point numbers quantization using NumPy.
Home-page: https://github.com/Hasenpfote/fpq
Author: Hasenpfote
Author-email: Hasenpfote36@gmail.com
License: UNKNOWN
Keywords: quantization,floating-point,vector,quaternion
Platform: UNKNOWN
Classifier: Programming Language :: Python
Classifier: Programming Language :: Python :: 3
Classifier: Programming Language :: Python :: 3.4
Classifier: Programming Language :: Python :: 3.5
Classifier: Programming Language :: Python :: 3.6
Classifier: Programming Language :: Python :: 3.7
Classifier: License :: OSI Approved :: MIT License
Classifier: Operating System :: OS Independent
Classifier: Development Status :: 4 - Beta
Classifier: Environment :: Other Environment
Classifier: Intended Audience :: Developers
Classifier: Topic :: Software Development :: Libraries :: Python Modules
Requires-Python: >=3.4
Requires-Dist: numpy (>=1.11.2)
Requires-Dist: numba (>=0.38.0); python_version >= "3.5"
